mhb_math/__init__.py
mhb_math/equations.py
mhb_math/functions.py
mhb_math-0.1.9.dist-info/LICENSE
mhb_math-0.1.9.dist-info/METADATA
mhb_math-0.1.9.dist-info/WHEEL
mhb_math-0.1.9.dist-info/top_level.txt
mhb_math-0.1.9.dist-info/RECORD
